MANIFEST.in
README.rst
setup.cfg
setup.py
Products/__init__.py
Products.PFGMasterSelect.egg-info/PKG-INFO
Products.PFGMasterSelect.egg-info/SOURCES.txt
Products.PFGMasterSelect.egg-info/dependency_links.txt
Products.PFGMasterSelect.egg-info/entry_points.txt
Products.PFGMasterSelect.egg-info/namespace_packages.txt
Products.PFGMasterSelect.egg-info/not-zip-safe
Products.PFGMasterSelect.egg-info/paster_plugins.txt
Products.PFGMasterSelect.egg-info/requires.txt
Products.PFGMasterSelect.egg-info/top_level.txt
Products/PFGMasterSelect/README.txt
Products/PFGMasterSelect/__init__.py
Products/PFGMasterSelect/browser.py
Products/PFGMasterSelect/config.py
Products/PFGMasterSelect/configure.zcml
Products/PFGMasterSelect/fields.py
Products/PFGMasterSelect/interfaces.py
Products/PFGMasterSelect/setuphandlers.py
Products/PFGMasterSelect/testing.py
Products/PFGMasterSelect/validators.py
Products/PFGMasterSelect/profiles/default/factorytool.xml
Products/PFGMasterSelect/profiles/default/import_steps.xml
Products/PFGMasterSelect/profiles/default/metadata.xml
Products/PFGMasterSelect/profiles/default/pfgmasterselect-various.txt
Products/PFGMasterSelect/profiles/default/propertiestool.xml
Products/PFGMasterSelect/profiles/default/rolemap.xml
Products/PFGMasterSelect/profiles/default/types.xml
Products/PFGMasterSelect/profiles/default/workflows.xml
Products/PFGMasterSelect/profiles/default/types/FormMasterMultiSelectStringField.xml
Products/PFGMasterSelect/profiles/default/types/FormMasterSelectStringField.xml
Products/PFGMasterSelect/tests/__init__.py
Products/PFGMasterSelect/tests/test.py