Metadata-Version: 1.1
Name: Products.PFGMasterSelect
Version: 0.2
Summary: Plone Formgen Fields using Master Select Widgets
Home-page: https://github.com/bpoettinger/Products.PFGMasterSelect
Author: Bernhard Pöttinger
Author-email: bernhard.poettinger@tngtech.com
License: GPL
Keywords: Plone PloneFormGen MasterSelectWidget
Platform: UNKNOWN
Classifier: Development Status :: 4 - Beta
Classifier: Framework :: Plone
Classifier: Framework :: Plone :: 4.3
Classifier: Intended Audience :: Developers
Classifier: Programming Language :: Python
Classifier: Programming Language :: Python :: 2.7
Classifier: License :: OSI Approved :: GNU General Public License (GPL)
Classifier: Operating System :: OS Independent
